automacdoc/__init__.py
automacdoc/automacdoc.py
automacdoc/main.py
src/__init__.py
src/automacdoc.py
AutoMacDoc-0.3.dist-info/LICENCE
AutoMacDoc-0.3.dist-info/METADATA
AutoMacDoc-0.3.dist-info/WHEEL
AutoMacDoc-0.3.dist-info/entry_points.txt
AutoMacDoc-0.3.dist-info/top_level.txt
AutoMacDoc-0.3.dist-info/RECORD
