Metadata-Version: 2.1
Name: AutoMacDoc
Version: 0.3
Summary: Automatic generation of documentation for python projects
Home-page: UNKNOWN
Author: Alexandre Kempf
Author-email: alexandre.kempf@¢ri-paris.org
License: UNKNOWN
Platform: UNKNOWN
Classifier: Programming Language :: Python :: 3
Classifier: License :: OSI Approved :: MIT License
Classifier: Operating System :: OS Independent
Requires-Dist: mkdocs
Requires-Dist: mkdocs-material
Requires-Dist: pymdown-extensions
